flask_simple_csrf/__init__.py
flask_simple_csrf/config.py
flask_simple_csrf-1.2.0.dist-info/LICENSE
flask_simple_csrf-1.2.0.dist-info/METADATA
flask_simple_csrf-1.2.0.dist-info/WHEEL
flask_simple_csrf-1.2.0.dist-info/top_level.txt
flask_simple_csrf-1.2.0.dist-info/RECORD
