Metadata-Version: 2.1
Name: flask-simple-csrf
Version: 1.2.0
Summary: Extremely simple, "Good Enough" csrf implemention for flask forms, no server side sessions required.
Home-page: https://github.com/cc-d/flask-simple-csrf
Author: Cary Carter
Author-email: ccarterdev@gmail.com
License: MIT
Platform: UNKNOWN
Classifier: License :: OSI Approved :: MIT License
Classifier: Programming Language :: Python :: 3
Classifier: Programming Language :: Python :: 3.7
Requires-Dist: Werkzeug (==0.16.0)
